<?xml version="1.0" encoding="UTF-8" ?>
<!DOCTYPE tiles-definitions PUBLIC
       "-//Apache Software Foundation//DTD Tiles Configuration 2.0//EN"
       "http://tiles.apache.org/dtds/tiles-config_2_0.dtd">
       
<!-- cs고객센터 : 게시판 -->
<tiles-definitions>
    <definition name="/board/listArticles" extends="baseLayout">
       <put-attribute name="title" value="고객센터 목록" />
       <put-attribute name="body" value="/WEB-INF/views/board/listArticles.jsp" />
    </definition>
    
     <definition name="/board/addNewArticle" extends="baseLayout">
       <put-attribute name="title" value="고객센터 글쓰기" />
       <put-attribute name="body" value="/WEB-INF/views/board/articleForm.jsp" />
    </definition>
    
    <!--     
    <definition name="/board/modifyArticle" extends="baseLayout">
       <put-attribute name="title" value="고객센터 수정페이지" />
       <put-attribute name="body" value="/WEB-INF/views/board/articleForm.jsp" />
    </definition>
     -->
    
    <definition name="/board/viewArticle" extends="baseLayout">
       <put-attribute name="title" value="고객센터 게시물" />
       <put-attribute name="body" value="/WEB-INF/views/board/viewArticle.jsp" />
    </definition>
    <!-- 
    <definition name="/board/addNewArticle" extends="baseLayout">
       <put-attribute name="title" value="고객센터 답글쓰기" />
       <put-attribute name="body" value="/WEB-INF/views/board/replyForm.jsp" />
    </definition>
    -->
</tiles-definitions>